netezza_import/__init__.py
netezza_import/main.py
netezza_import-0.1.0.dist-info/METADATA
netezza_import-0.1.0.dist-info/WHEEL
netezza_import-0.1.0.dist-info/entry_points.txt
netezza_import-0.1.0.dist-info/top_level.txt
netezza_import-0.1.0.dist-info/RECORD
